ypconnector-1.1.2.dist-info/METADATA
ypconnector-1.1.2.dist-info/RECORD
ypconnector-1.1.2.dist-info/WHEEL
ypconnector-1.1.2.dist-info/top_level.txt
yplib/__init__.py
yplib/ypconnector.py
