Metadata-Version: 2.1
Name: ypconnector
Version: 1.1.2
Summary: Python SDK for integrating APIs published via Yappes platform
Home-page: https://github.com/yappes-technologies/ypconnector-python
Author: YappesLib
Author-email: info@yappes.com
License: UNKNOWN
Platform: UNKNOWN
Classifier: Programming Language :: Python :: 3
Classifier: License :: OSI Approved :: MIT License
Classifier: Operating System :: OS Independent
Requires-Dist: requests
